granloader/__init__.py
granloader/app.py
granloader/main.py
granloader/utils.py
granloader-3.0.1.dist-info/LICENSE.txt
granloader-3.0.1.dist-info/METADATA
granloader-3.0.1.dist-info/WHEEL
granloader-3.0.1.dist-info/entry_points.txt
granloader-3.0.1.dist-info/top_level.txt
granloader-3.0.1.dist-info/RECORD
