Metadata-Version: 2.1
Name: granloader
Version: 3.0.1
License-File: LICENSE.txt
Requires-Dist: yt-dlp ==2023.12.30
Requires-Dist: ffmpeg-python ==0.2.0
Requires-Dist: ffmpeg ==1.4
Requires-Dist: requests
